GCL/__init__.py
GCL/utils.py
GCL/augmentors/__init__.py
GCL/augmentors/augmentor.py
GCL/augmentors/edge_adding.py
GCL/augmentors/edge_attr_masking.py
GCL/augmentors/edge_removing.py
GCL/augmentors/feature_dropout.py
GCL/augmentors/feature_masking.py
GCL/augmentors/functional.py
GCL/augmentors/identity.py
GCL/augmentors/markov_diffusion.py
GCL/augmentors/node_dropping.py
GCL/augmentors/node_shuffling.py
GCL/augmentors/ppr_diffusion.py
GCL/augmentors/rw_sampling.py
GCL/eval/__init__.py
GCL/eval/eval.py
GCL/eval/logistic_regression.py
GCL/eval/random_forest.py
GCL/eval/svm.py
GCL/losses/__init__.py
GCL/losses/barlow_twins.py
GCL/losses/bootstrap.py
GCL/losses/infonce.py
GCL/losses/jsd.py
GCL/losses/losses.py
GCL/losses/triplet.py
GCL/losses/vicreg.py
GCL/models/__init__.py
GCL/models/contrast_model.py
GCL/models/samplers.py
PyGCL-0.1.2.dist-info/LICENSE
PyGCL-0.1.2.dist-info/METADATA
PyGCL-0.1.2.dist-info/WHEEL
PyGCL-0.1.2.dist-info/top_level.txt
PyGCL-0.1.2.dist-info/RECORD
