Metadata-Version: 2.1
Name: PyGCL
Version: 0.1.2
Summary: PyGCL: Graph Contrastive Learning for PyTorch
Home-page: https://github.com/GraphCL/PyGCL
Author: Yanqiao Zhu
Author-email: i@sxkdz.me
License: UNKNOWN
Project-URL: Bug Tracker, https://github.com/GraphCL/PyGCL/issues
Keywords: PyTorch,Graph-Neural-Networks,Graph-Contrastive-Learning
Platform: UNKNOWN
Classifier: Programming Language :: Python :: 3
Classifier: License :: OSI Approved :: MIT License
Classifier: Operating System :: OS Independent
Requires-Python: >=3.8
License-File: LICENSE
Requires-Dist: torch (>=1.9)
Requires-Dist: torch-geometric (>=1.7)
Requires-Dist: numpy
Requires-Dist: tqdm
Requires-Dist: scipy
Requires-Dist: networkx
Requires-Dist: scikit-learn
